flowfsm/__init__.py
flowfsm/config/__init__.py
flowfsm/config/loader.py
flowfsm/config/parser.py
flowfsm/core/__init__.py
flowfsm/core/base.py
flowfsm/core/errors.py
flowfsm/core/event.py
flowfsm/core/state.py
flowfsm/core/transition.py
flowfsm/core/workflow.py
flowfsm/runtime/__init__.py
flowfsm/runtime/executor.py
flowfsm/runtime/hooks.py
flowfsm/runtime/listeners.py
flowfsm/runtime/logger.py
flowfsm/utils/__init__.py
flowfsm/utils/decorators.py
flowfsm/visualisation/__init__.py
flow_fsm-1.0.0.dist-info/LICENSE
flow_fsm-1.0.0.dist-info/METADATA
flow_fsm-1.0.0.dist-info/WHEEL
flow_fsm-1.0.0.dist-info/top_level.txt
flow_fsm-1.0.0.dist-info/RECORD
