Metadata-Version: 2.1
Name: flow-fsm
Version: 1.0.0
Summary: A versatile Python framework for finite state machines and workflows.
Author-email: Akshita Dixit <akshitadixit.int@gmail.com>
Requires-Python: >=3.13
License-File: LICENSE
Requires-Dist: pyyaml>=6.0.2
